youtube_transcript_api/__init__.py
youtube_transcript_api/__main__.py
youtube_transcript_api/_api.py
youtube_transcript_api/_cli.py
youtube_transcript_api/_errors.py
youtube_transcript_api/_html_unescaping.py
youtube_transcript_api/_settings.py
youtube_transcript_api/_transcripts.py
youtube_transcript_api/formatters.py
youtube_transcript_api/test/__init__.py
youtube_transcript_api/test/test_api.py
youtube_transcript_api/test/test_cli.py
youtube_transcript_api/test/test_formatters.py
youtube_transcript_api/test/assets/__init__.py
youtube_transcriptor/__init__.py
youtube_transcriptor/__main__.py
youtube_transcriptor/_api.py
youtube_transcriptor/_cli.py
youtube_transcriptor/_errors.py
youtube_transcriptor/_html_unescaping.py
youtube_transcriptor/_settings.py
youtube_transcriptor/_transcripts.py
youtube_transcriptor/formatters.py
youtube_transcriptor/test/__init__.py
youtube_transcriptor/test/test_api.py
youtube_transcriptor/test/test_cli.py
youtube_transcriptor/test/test_formatters.py
youtube_transcriptor/test/assets/__init__.py
youtube_transcriptor-0.6.3.dist-info/LICENSE
youtube_transcriptor-0.6.3.dist-info/METADATA
youtube_transcriptor-0.6.3.dist-info/WHEEL
youtube_transcriptor-0.6.3.dist-info/entry_points.txt
youtube_transcriptor-0.6.3.dist-info/top_level.txt
youtube_transcriptor-0.6.3.dist-info/RECORD
