Metadata-Version: 2.1
Name: youtube-transcriptor
Version: 0.6.3
Summary: This is an python API which allows you to get the transcripts/subtitles for a given YouTube video. It also works for automatically generated subtitles, supports translating subtitles and it does not require a headless browser, like other selenium based solutions do!
Home-page: https://github.com/doggy8088/youtube-transcript-api
Author: Will Huang
Author-email: doggy.huang@gmail.com
Keywords: youtube-api subtitles youtube transcripts transcript subtitle youtube-subtitles youtube-transcripts cli
Classifier: Programming Language :: Python :: 3.5
Classifier: Programming Language :: Python :: 3.6
Classifier: Programming Language :: Python :: 3.7
Classifier: Programming Language :: Python :: 3.8
Classifier: License :: OSI Approved :: MIT License
Classifier: Operating System :: OS Independent
License-File: LICENSE
Requires-Dist: requests
